iife/__init__.py
invoke_iife-1.1.0.dist-info/LICENSE
invoke_iife-1.1.0.dist-info/WHEEL
invoke_iife-1.1.0.dist-info/METADATA
invoke_iife-1.1.0.dist-info/RECORD
