Metadata-Version: 2.1
Name: invoke-iife
Version: 1.1.0
Summary: Bringing the fun of immediately-invoked function expressions to Python!
Home-page: https://torshepherd.github.io/iife-py
License: MIT
Author: Tor Shepherd
Author-email: tor.aksel.shepherd@gmail.com
Requires-Python: >=3.7,<4.0
Classifier: Development Status :: 4 - Beta
Classifier: Intended Audience :: Developers
Classifier: License :: OSI Approved :: MIT License
Classifier: Operating System :: OS Independent
Classifier: Programming Language :: Python
Classifier: Programming Language :: Python :: 3
Classifier: Programming Language :: Python :: 3.10
Classifier: Programming Language :: Python :: 3.7
Classifier: Programming Language :: Python :: 3.8
Classifier: Programming Language :: Python :: 3.9
Classifier: Topic :: Software Development :: Libraries :: Python Modules
Project-URL: Documentation, https://torshepherd.github.io/iife-py
Project-URL: Repository, https://github.com/torshepherd/iife-py
